{
  "objective": {
    "body": "Recognizable Software Engineer Skill, Recognizable Coding Skill, 9-Year Java Coding Experience.",
    "heading": "Traits",
    "visible": true
  },
  "work": {
    "heading": "Work Experience",
    "items": [
      {
        "company": "Sina Weibo, Chengdu R&D, Chengdu",
        "position": "Software engineer",
        "endDate": "now",
        "startDate": "2016-08-26",
        "website": "https://weibo.com"
      },
      {
        "company": "Modan, ShenZhen",
        "endDate": "2016-01-28",
        "position": "Web Developer",
        "startDate": "2015-06-27"
      },
      {
        "company": "Yonyou NC EC Department, Beijing",
        "endDate": "2015-06-20",
        "position": "Java Developer",
        "startDate": "2014-05-21",
        "website": "https://www.yonyou.com"
      },
      {
        "company": "Yonyou, Software Engineer Department",
        "endDate": "2014-05-20",
        "position": "Junior Java Developer",
        "startDate": "2012-09-01",
        "website": "https://www.yonyou.com"
      }
    ],
    "visible": true
  },
  "skills": {
    "heading": "Skills",
    "items": [
      {
        "isVisible": true,
        "level": "Advanced",
        "name": "Java"
      },
      {
        "isVisible": true,
        "level": "Advanced",
        "name": "Design | OOP UML"
      },
      {
        "isVisible": true,
        "level": "Advanced",
        "name": "MicroService | Registration-Center Config-Center Observability LB etc..."
      },
      {
        "isVisible": true,
        "level": "Advanced",
        "name": "Middleware | Mysql Redis Kafka ES etc..."
      },
      {
        "isVisible": true,
        "level": "Intermediate",
        "name": "Devops | Shell K8S Istio Docker etc..."
      },
      {
        "isVisible": true,
        "level": "Intermediate",
        "name": "Computer | Linux Common-Protocols Common-Algorithm"
      },
      {
        "isVisible": true,
        "level": "Intermediate",
        "name": "Language | Js Python Bash"
      }
    ],
    "visible": true
  },
  "projects": {
    "heading": "Projects",
    "items": [
      {
        "startDate": "2019-02-01",
        "endDate": "now",
        "summary": "* About the app\n    - Ins-like image-based content distribution software, users share and consume images on the app.\n    - Users can interact with the content (refer to, comments, likes), and can interact with other users (mutual fans, private chats or through water drops (a currency of Oasis app))\n    - Users can get water drops (a currency of the Oasis app) when using Oasis products.\n    - Oasis and Weibo are connected, dynamic exchanges their contents.\n    - The estimated carrying capacity of the project was 300K DAU, which was changed to 10M DAU at the initial stage of the official launch.\n* Participate in the design and construction of the server architecture\n    - Server version 1.0 app dau rises rapidly, and we went to microservice by splitting codes across departments and teams. \n    - Server version 2.0 we adopt K8S, using it and its ecology to realize the platformization of logging, monitoring, and link tracking, and realizes convenient functions related to Devops.\n* Duty of Analyzing, designing and coding\n    - Responsible for main status publisher, main feed stream, user-defined data, intercommunication with Weibo and other related businesses.\n    - Use UML tools to disassemble and refine requirements, produce sequence diagrams, state diagrams and object designs, etc., and then pull in the team to review and code based on this.\n    - Object-oriented coding, striving for code readability, easy to expand, easy to scale\n    - Write Junit unit tests, integration tests across teams/departments if possible, to ensure delivery quality.\n* Technology stack\n    - Springboot and its eco-system.\n    - Internet middleware such as Mysql, Redis, Kafka, Elasticsearch, etc.\n    - Docker containerization.\n    - K8S service scaling, grayscale publishing, sidecar mode (istio) log collection, JVM performance and business monitoring, microservice link tracking.\n* Achievement\n    - Completed milestones such as 30K DAUs and 1M DAUs.\n    - Eventual consistent design and coding experience for millions of daily active products.\n    - Experience accumulated in microservices",
        "title": "Oasis app"
      },
      {
        "startDate": "2017-04-24",
        "endDate": "2019-02-01",
        "summary": "* Responsible for three engineering projects\n    - Weibo picture classification\n       - Using the Tensorflow framework for training and classifying, and the images were tagged and sent to the Weibo app team for subsequent use.\n    - Weather image classification\n       - Train and classify weather pictures (cloudy, sunny, rainy, snow, etc.), tag the pictures and send them to the weather app team for subsequent use.\n    - Similar music Recognition\n       - Find the short video containing the music, tag it and send it to short video app team for subsequent use.\n* Technology stack\n    - Python scripting\n    - Tensorflow\n    - Springboot and its eco-system\n    - Kafka, Redis, etc. as middleware for cross-departmental data transmission\n* Achievement\n    - Greatly reduce the workload of manual labeling operations.\n    - Improve the user experience of the App and increase the user's usage time.",
        "title": "Machine learning"
      },
      {
        "startDate": "2016-08-26",
        "endDate": "2017-04-24",
        "summary": "* About the supporting platform\n    - Management + Operation All apps approved by Chengdu R&D Center\n    - Including 鲜城(2014-16) 随手拍(15-17) 爱动(17-19) 绿洲(19-now)\n* Reconstruct the entire historical code of the supporting platform built during the years 14-15.\n    - Realize front and back end separation.\n    - Using the Reactjs framework, introducing best practices.\n* Technology stack\n    - Springboot\n    - Mysql, Redis, Docker\n    - Nodejs, React, Redux, Ant Design, React Saga, Webpack\n* Achievement\n    - Refactoring the historical code to greatly improve the development efficiency of the team.\n    - Implement and share new technologies to broaden the team's vision.\n",
        "title": "App supporting platform"
      },
      {
        "startDate": "2015-06-27",
        "endDate": "2016-01-28",
        "summary": "* About Modan\n    - Imitation ps, xbox. Based on Android operating system, the box is connected to the TV, and users play paid/free games on it.\n    - The operation interface of the box is using web technology. It interacts with the server to realize the account system and pay-to-play process.\n* Responsible for all UI interface\n    - Gaming-Box side: account UI, store UI, feedback UI, social-related UI etc.\n    - Management side: account UI, operator management UI, game player management UI etc.\n* Technology stack\n    - Nodejs, Expressjs\n    - Reactjs, Ant Design, Webpack\n    ",
        "title": "Modan gaming platform"
      },
      {
        "startDate": "2014-05-13",
        "endDate": "2015-06-15",
        "summary": "* About the website\n    - E-commerce website for large-scale procurement between enterprises.\n* What I did\n    - Code the Reseller Organization Relations section\n    - Statistical sales and expenditures of dealers, generate reports\n    - Introduction and sharing of new tools\n* new tools\n    - Investigate, share, realize Reactjs, abandon JSP technology, separate front and back ends, and reconstruct historical code.\n    - Based on Reactjs, we made a set of UI internal components that simply satisfy the portal website.\n    - Assign requirements to a 3-person team and review the code.\n* Technology stack\n    - SpringMVC Hibernate Struts Mysql \n    - Reactjs\n* Achievements\n    - Separation of front-end and back-end to improve team efficiency.",
        "title": "NC Dealer Portal"
      },
      {
        "startDate": "2013-03-28",
        "endDate": "2014-05-17",
        "summary": "* About the app\n    - A tool for driving school to check attendance of students/instructors.\n    - Based on attendance and student evaluation, form the basis for coach assessment.\n    - Assist in managing the daily activities of the driving school\n* What I did\n    - Code the business of the student fingerprint management.\n    - Code student management business.\n    - Code student attendance, coach attendance business.\n    - Code coach reward business.\n    - Code the daily activities business of the driving school, and output the activity income and expenditure report.\n* Technology stack\n    - SpringMVC Hibernate Struts Mysql",
        "title": "Driving school app"
      },
      {
        "startDate": "2012-08-25",
        "endDate": "2013-03-20",
        "summary": "* About\n    - Like erp system for supermarket\n* What I did\n    - Code merchant organization relationship business.\n    - Code supermarket's staff organization business. \n    - Code supermarket's daily activities, and report its income and expenditure.\n    - Code supermarket financial income related code.\n* Technology stack\n    - SpringMVC Hibernate Struts Mysql",
        "title": "Supermarket management platform"
      }
    ],
    "visible": true
  },
  "awards": {
    "heading": "Awards",
    "items": [
      {
        "awarder": "Yonyou",
        "date": "2014-12-13",
        "id": "",
        "summary": "",
        "title": "Outstanding Yonyou New Comer"
      },
      {
        "awarder": "Weibo",
        "date": "2017-12-01",
        "id": "",
        "summary": "",
        "title": "Weibo innovation award"
      },
      {
        "awarder": "Weibo",
        "date": "2020-01-15",
        "id": "",
        "summary": "",
        "title": "Team of The Year"
      }
    ],
    "visible": true
  },
  "certifications": {
    "heading": "Certifications",
    "items": [
      {
        "date": "2012-07-01",
        "issuer": "USTC",
        "summary": "",
        "title": "Diploma"
      },
      {
        "date": "2012-07-01",
        "issuer": "USTC",
        "summary": "",
        "title": "Bachelor's Degree"
      }
    ],
    "visible": true
  },
  "education": {
    "heading": "Education",
    "items": [
      {
        "degree": "Bachelors",
        "startDate": "2007-09-01",
        "endDate": "2012-08-01",
        "field": "Statistics",
        "institution": "University of Science And Technology of China",
        "summary": ""
      }
    ],
    "visible": true
  },
  "hobbies": {
    "heading": "Hobbies",
    "items": [
      {
        "name": "Engineer"
      },
      {
        "name": "Reading"
      },
      {
        "name": "Science"
      },
      {
        "name": "Soccer"
      },
      {
        "name": "DIY"
      },
      {
        "name": "Survival"
      }
    ],
    "visible": true
  },

  "languages": {
    "heading": "Languages",
    "items": [
      {
        "fluency": "Native Tongue",
        "name": "Mandarin"
      },
      {
        "fluency": "Good",
        "name": "English"
      }
    ],
    "visible": true
  },
  "metadata": {
    "colors": {
      "background": "#FFFFFF",
      "primary": "#4CAF50",
      "text": "#212121"
    },
    "font": "Titillium Web",
    "fontSize": "10",
    "language": "zh",
    "layout": {
      "castform": [
        [
          "awards",
          "certifications",
          "languages",
          "hobbies"
        ],
        [
          "objective",
          "work",
          "education",
          "skills",
          "projects",
          "references"
        ]
      ],
      "celebi": [
        [
          "awards",
          "certifications",
          "languages",
          "hobbies"
        ],
        [
          "objective",
          "work",
          "education",
          "skills",
          "projects",
          "references"
        ]
      ],
      "gengar": [
        [
          "objective",
          "skills"
        ],
        [
          "awards",
          "certifications",
          "languages",
          "references",
          "hobbies"
        ],
        [
          "work",
          "education",
          "projects"
        ]
      ],
      "glalie": [
        [
          "awards",
          "certifications",
          "hobbies"
        ],
        [
          "objective",
          "work",
          "education",
          "skills",
          "projects",
          "languages",
          "references"
        ]
      ],
      "onyx": [
        [
          "objective",
          "education",
          "skills",
          "work",
          "projects"
        ],
        [
          "languages",
          "awards",
          "certifications",
          "hobbies"
        ],
        [
          "references"
        ]
      ],
      "pikachu": [
        [
          "skills",
          "languages",
          "hobbies",
          "awards",
          "certifications"
        ],
        [
          "work",
          "education",
          "projects",
          "references"
        ]
      ]
    },
    "template": "onyx"
  },

  "preview": "",
  "profile": {
    "address": {
      "city": "ChengDu",
      "line1": "TianFu New District",
      "pincode": 230022
    },
    "birthDate": "1989-02-21",
    "email": "luoxiaobatman@gmail.com",
    "firstName": "Ryan",
    "heading": "Profile",
    "lastName": "Luo",
    "phone": "+86 13521025643",
    "subtitle": "Java Developer"
  },

  "public": true,
  "references": {
    "heading": "References",
    "items": [
      {
        "email": "willywonka@goldenticket.com",
        "id": "168339fd-3c4b-4f2f-bd3a-ef184be81700",
        "name": "Willy Wonka",
        "phone": "+1 (802) 234-2398",
        "position": "CEO at Chocolate Factory",
        "summary": ""
      },
      {
        "email": "elanmusk@nottesla.com",
        "id": "350465b9-9989-43cc-b97e-4115b8980304",
        "name": "Elangovan Musk",
        "phone": "+91 93893 34353",
        "position": "CEO at Newton Motors",
        "summary": ""
      },
      {
        "email": "l.beasley@carsonlogistics.com",
        "id": "94e3447b-0a78-4fb7-b14d-591982d35320",
        "name": "Lorraine Beasley",
        "phone": "+1 661-808-4188",
        "position": "Head of HR, Carson Logistics",
        "summary": ""
      }
    ],
    "visible": false
  },

  "social": {
    "heading": "Social Network",
    "items": [
      {
        "id": "a832b37d-f11d-4a80-8b4d-24796e571b17",
        "network": "Instagram",
        "url": "https://pillai.xyz/instagram",
        "username": "AmruthPillai",
        "isVisible": false
      },
      {
        "id": "a72107fa-a4a5-407d-9e85-39bdb9c0b11a",
        "network": "Twitter",
        "url": "https://pillai.xyz/twitter",
        "username": "KingOKings",
        "isVisible": false
      },
      {
        "id": "1dd46fdd-b3a3-4786-89ce-2e77c0823aba",
        "network": "LinkedIn",
        "url": "https://pillai.xyz/linkedin",
        "username": "AmruthPillai",
        "isVisible": false
      }
    ],
    "visible": true
  }

}